{"analysis_date": "2025-12-09 16:42:29", "target_trading_date": "20251020", "market_pattern": "normal", "regime_data": {"take_profit_pct": 0.18, "stop_loss_pct": 0.09, "trailing_stop_enabled": true, "max_hold_days": 7, "min_hold_days": 2, "late_trend_filter": {"ma_threshold": 1.25, "short_gain_threshold": 0.3, "mid_gain_threshold": 0.5, "volume_multiplier": 3.0}, "regime": "normal"}, "strategy_config": {"profit_target_pct": 18.0, "stop_loss_pct": 9.0, "max_position_pct": 0.15}, "portfolio_config": {"initial_cash": 600000, "max_positions": 8, "total_allocated": 486359.0}, "total_orders": 8, "smart_orders": [{"symbol": "002756.SZ", "name": "\u6c38\u5174\u6750\u6599", "analysis_date": "2025-12-09 16:34:07", "current_price": 38.76, "buy_price": 38.94, "sell_take_profit_price": 45.95, "sell_stop_loss_price": 36.6, "buy_quantity": 1900, "position_value": 73986.0, "technical_indicators": {"rsi": 64.72, "bb_position": 119.03, "atr": 1.32, "recent_high": 39.48, "recent_low": 33.37}, "risk_metrics": {"potential_gain_pct": 18.0, "potential_loss_pct": -6.01, "risk_reward_ratio": 3.0, "position_risk_pct": 12.33}, "market_data": {"turnover_rate": 8.95, "volume_ratio": 2.81, "pe": 20.03}}, {"symbol": "600388.SH", "name": "\u9f99\u51c0\u73af\u4fdd", "analysis_date": "2025-12-09 16:34:07", "current_price": 15.09, "buy_price": 15.13, "sell_take_profit_price": 17.85, "sell_stop_loss_price": 14.22, "buy_quantity": 5000, "position_value": 75650.0, "technical_indicators": {"rsi": 73.05, "bb_position": 103.72, "atr": 0.54, "recent_high": 15.24, "recent_low": 13.28}, "risk_metrics": {"potential_gain_pct": 17.98, "potential_loss_pct": -6.01, "risk_reward_ratio": 2.99, "position_risk_pct": 12.61}, "market_data": {"turnover_rate": 1.59, "volume_ratio": 0.9, "pe": 23.08}}]}