{"pick_date": "2025-12-11 13:48:41", "base_date": "20250711", "target_trading_date": "20250714", "market_pattern": "bull", "regime_data": {"take_profit_pct": 0.18, "stop_loss_pct": 0.06, "trailing_stop_enabled": true, "max_hold_days": 10, "min_hold_days": 3, "late_trend_filter": {"ma_threshold": 1.6, "short_gain_threshold": 0.6, "mid_gain_threshold": 1.0, "volume_multiplier": 5.0}, "regime": "bull"}, "selected_stocks": [{"rank": 1, "symbol": "002640.SZ", "score": 65.16}, {"rank": 2, "symbol": "603093.SH", "score": 59.72}, {"rank": 3, "symbol": "601519.SH", "score": 51.45}, {"rank": 4, "symbol": "002104.SZ", "score": 46.67}, {"rank": 6, "symbol": "000607.SZ", "score": 33.22}, {"rank": 7, "symbol": "600446.SH", "score": 31.86}, {"rank": 8, "symbol": "601696.SH", "score": 30.41}, {"rank": 9, "symbol": "600392.SH", "score": 27.34}]}