{"pick_date": "2026-05-15 17:02:05", "base_date": "20250821", "target_trading_date": "20250822", "market_pattern": "bull", "regime_data": {"take_profit_pct": 0.18, "stop_loss_pct": 0.06, "trailing_stop_enabled": true, "max_hold_days": 10, "min_hold_days": 3, "late_trend_filter": {"ma_threshold": 1.6, "short_gain_threshold": 0.6, "mid_gain_threshold": 1.0, "volume_multiplier": 5.0}, "regime": "bull"}, "selected_stocks": [{"rank": 1, "symbol": "301628.SZ", "name": "\u5f3a\u8fbe\u7535\u8def", "score": 100.0}, {"rank": 2, "symbol": "688283.SH", "name": "\u5764\u6052\u987a\u7ef4", "score": 100.0}, {"rank": 3, "symbol": "600535.SH", "name": "\u5929\u58eb\u529b", "score": 100.0}, {"rank": 4, "symbol": "688391.SH", "name": "\u949c\u6cc9\u79d1\u6280", "score": 100.0}, {"rank": 5, "symbol": "603057.SH", "name": "\u7d2b\u71d5\u98df\u54c1", "score": 100.0}, {"rank": 6, "symbol": "002299.SZ", "name": "\u5723\u519c\u53d1\u5c55", "score": 100.0}, {"rank": 7, "symbol": "000011.SZ", "name": "\u6df1\u7269\u4e1aA", "score": 100.0}, {"rank": 8, "symbol": "601995.SH", "name": "\u4e2d\u91d1\u516c\u53f8", "score": 95.0}]}