{"pick_date": "2025-12-11 15:35:38", "base_date": "20250707", "target_trading_date": "20250708", "market_pattern": "bull", "regime_data": {"take_profit_pct": 0.18, "stop_loss_pct": 0.06, "trailing_stop_enabled": true, "max_hold_days": 10, "min_hold_days": 3, "late_trend_filter": {"ma_threshold": 1.6, "short_gain_threshold": 0.6, "mid_gain_threshold": 1.0, "volume_multiplier": 5.0}, "regime": "bull"}, "selected_stocks": [{"rank": 1, "symbol": "600475.SH", "score": 75.48, "source": "BOTH"}, {"rank": 2, "symbol": "002366.SZ", "score": 68.6, "source": "BOTH"}, {"rank": 3, "symbol": "002721.SZ", "score": 65.8, "source": "BOTH"}, {"rank": 4, "symbol": "600513.SH", "score": 56.7, "source": "BOTH"}, {"rank": 5, "symbol": "600101.SH", "score": 53.7, "source": "BOTH"}, {"rank": 6, "symbol": "603716.SH", "score": 51.07, "source": "BOTH"}, {"rank": 7, "symbol": "600744.SH", "score": 50.1, "source": "BOTH"}, {"rank": 8, "symbol": "000560.SZ", "score": 46.42, "source": "BOTH"}]}