{"pick_date": "2025-12-09 19:49:29", "base_date": "20251031", "target_trading_date": "20251103", "market_pattern": "bull", "regime_data": {"take_profit_pct": 0.18, "stop_loss_pct": 0.06, "trailing_stop_enabled": true, "max_hold_days": 10, "min_hold_days": 3, "late_trend_filter": {"ma_threshold": 1.6, "short_gain_threshold": 0.6, "mid_gain_threshold": 1.0, "volume_multiplier": 5.0}, "regime": "bull"}, "selected_stocks": [{"rank": 1, "symbol": "001301.SZ", "score": 55.95}, {"rank": 2, "symbol": "001203.SZ", "score": 55.0}, {"rank": 3, "symbol": "002759.SZ", "score": 50.19}, {"rank": 4, "symbol": "000688.SZ", "score": 48.37}, {"rank": 5, "symbol": "603686.SH", "score": 41.36}, {"rank": 6, "symbol": "002163.SZ", "score": 41.15}, {"rank": 7, "symbol": "000762.SZ", "score": 35.0}, {"rank": 8, "symbol": "002173.SZ", "score": 34.71}]}